{
  "metadata": {
    "name": "Hyperclasse Link Human And Car",
    "purpose": "Reference HBDS model for Hyperclasse Link Human And Car.",
    "regressionTags": [
      "model",
      "hyperclasse",
      "link",
      "human",
      "car",
      "links",
      "hyperclass"
    ],
    "sceneSettings": {
      "background": "#eef2f6",
      "ambient": 0,
      "front": 0,
      "sources": [
        {
          "intensity": 1,
          "direction": {
            "x": -5.734,
            "y": 7,
            "z": 14.937
          }
        },
        {
          "intensity": 0.6,
          "direction": {
            "x": 0,
            "y": 11.314,
            "z": 11.314
          }
        }
      ]
    },
    "layout": {
      "algorithm": "radial",
      "fit": {
        "padding": 1.18,
        "fitHeightDistance": 10.4131,
        "fitWidthDistance": 12.7553,
        "distance": 12.832,
        "diagramWidth": 14.1075,
        "diagramHeight": 8.23,
        "diagramDepth": 0.13,
        "radius": 8.1666,
        "center": {
          "x": -0.5538,
          "y": 0,
          "z": 0.065
        },
        "cameraAspect": 1.3994,
        "cameraFov": 50,
        "mode": "userView",
        "savedView": true,
        "subjectCount": 4
      }
    },
    "font": {
      "size": 20,
      "family": "Arial, sans-serif",
      "bold": false,
      "italic": false,
      "underline": false
    }
  },
  "hypergraph": {
    "class": [
      {
        "id": "hyperclasse_link_human_and_car_3",
        "name": "Car",
        "type": "roundedRectangle",
        "attributes": [
          "Make",
          "Model",
          "Year",
          "VIN",
          "Color",
          "Mileage",
          "Engine type",
          "Fuel type",
          "Transmission",
          "License plate",
          "Owner"
        ],
        "position": {
          "x": 5,
          "y": 0,
          "z": 0
        },
        "size": {
          "width": 2.2,
          "height": 2.5
        },
        "rendering": {
          "class": {
            "color": "#00BFFF",
            "material": "metallic",
            "borderColor": "#000080",
            "borderWidth": 0.02,
            "cornerRadius": 0.1
          },
          "attributes": {
            "checkboxColor": "#A9A9A9",
            "checkboxMaterial": "metallic",
            "shape": "square",
            "size": {
              "width": 0.1,
              "height": 0.1
            },
            "font": {
              "size": 14
            }
          },
          "connections": {
            "lineColor": "#000000",
            "lineWidth": 0.01
          },
          "textColor": "#000000"
        }
      },
      {
        "id": "hyperclasse_link_human_and_car_100",
        "name": "Human",
        "type": "hyperclass",
        "attributes": [
          "Last name",
          "First name",
          "Middle name",
          "Age",
          "Weight",
          "Height",
          "Sex",
          "Date of birth",
          "Place of birth",
          "Nationality",
          "Marital status",
          "Occupation",
          "Education level",
          "Address",
          "Phone number",
          "Email"
        ],
        "position": {
          "x": -5,
          "y": 6.123233995736766e-16,
          "z": 0
        },
        "size": {
          "width": 5.215000000000001,
          "height": 8.23
        },
        "rendering": {
          "class": {
            "color": "#ECECEC",
            "material": "metallic",
            "borderColor": "#333333",
            "borderWidth": 0.02,
            "cornerRadius": 0.1,
            "metalness": 0.42,
            "roughness": 0.28,
            "emissiveIntensity": 0.035
          },
          "attributes": {
            "checkboxColor": "#A9A9A9",
            "checkboxMaterial": "metallic",
            "shape": "square",
            "size": {
              "width": 0.1,
              "height": 0.1
            },
            "font": {
              "size": 14
            }
          },
          "connections": {
            "lineColor": "#555555",
            "lineWidth": 0.01
          },
          "textColor": "#000000"
        },
        "children": [
          "hyperclasse_link_human_and_car_1",
          "hyperclasse_link_human_and_car_2"
        ]
      },
      {
        "id": "hyperclasse_link_human_and_car_1",
        "name": "Man",
        "type": "roundedRectangle",
        "position": {
          "x": -6.002499999999999,
          "y": 1.7150000000000012,
          "z": 0
        },
        "size": {
          "width": 1.8,
          "height": 3
        },
        "rendering": {
          "class": {
            "color": "#ADD8E6",
            "material": "metallic",
            "borderColor": "#000080",
            "borderWidth": 0.02,
            "cornerRadius": 0.1
          },
          "textColor": "#000000",
          "attributes": {
            "font": {
              "size": 14
            }
          }
        },
        "attributes": [
          "Beard Style",
          "Voice Pitch",
          "Shoulder-to-Hip Ratio",
          "Favorite Sport",
          "Typical Tie Knot"
        ],
        "parentClassId": "hyperclasse_link_human_and_car_100"
      },
      {
        "id": "hyperclasse_link_human_and_car_2",
        "name": "Woman",
        "type": "roundedRectangle",
        "position": {
          "x": -6.057499999999999,
          "y": -2.064999999999999,
          "z": 0
        },
        "size": {
          "width": 1.8,
          "height": 3
        },
        "rendering": {
          "class": {
            "color": "#FFB6C1",
            "material": "metallic",
            "borderColor": "#800000",
            "borderWidth": 0.02,
            "cornerRadius": 0.1
          },
          "textColor": "#000000",
          "attributes": {
            "font": {
              "size": 14
            }
          }
        },
        "attributes": [
          "Maiden Name",
          "Hip-to-Waist Ratio",
          "Hairstyle",
          "Zodiac Sign",
          "Preferred Handbag Style"
        ],
        "parentClassId": "hyperclasse_link_human_and_car_100"
      }
    ],
    "link": [
      {
        "id": "hyperclasse_link_human_and_car_link_1001",
        "name": "Owns",
        "type": "tube",
        "rendering": {
          "labelText": "Owns",
          "orthogonalStyle": "auto",
          "lineColor": "#3498db",
          "lineWidth": 0.02,
          "lineStyle": "dashed",
          "textColor": "#2980b9",
          "labelFontSize": 22
        },
        "sourceClassId": "hyperclasse_link_human_and_car_100",
        "targetClassId": "hyperclasse_link_human_and_car_3",
        "allowSelfLink": true
      },
      {
        "id": "hyperclasse_link_human_and_car_link_1002",
        "name": "Drives",
        "type": "arrow",
        "rendering": {
          "labelText": "Drives",
          "orthogonalStyle": "auto",
          "lineColor": "#2ecc71",
          "lineWidth": 0.02,
          "arrowheadSize": 0.1,
          "textColor": "#27ae60",
          "labelFontSize": 22
        },
        "sourceClassId": "hyperclasse_link_human_and_car_100",
        "targetClassId": "hyperclasse_link_human_and_car_3",
        "allowSelfLink": true
      },
      {
        "id": "hyperclasse_link_human_and_car_link_1003",
        "name": "Married To",
        "type": "bidirectional-arrow",
        "rendering": {
          "labelText": "Married To",
          "orthogonalStyle": "auto",
          "lineColor": "#e74c3c",
          "lineWidth": 0.02,
          "arrowheadSize": 0.1,
          "textColor": "#c0392b",
          "labelFontSize": 22
        },
        "sourceClassId": "hyperclasse_link_human_and_car_1",
        "targetClassId": "hyperclasse_link_human_and_car_2",
        "allowSelfLink": true
      },
      {
        "id": "hyperclasse_link_human_and_car_link_1004",
        "name": "Sibling Of",
        "type": "tube",
        "rendering": {
          "labelText": "Sibling Of",
          "orthogonalStyle": "auto",
          "lineColor": "#9b59b6",
          "lineWidth": 0.015,
          "lineStyle": "dotted",
          "textColor": "#8e44ad",
          "labelFontSize": 22
        },
        "sourceClassId": "hyperclasse_link_human_and_car_1",
        "targetClassId": "hyperclasse_link_human_and_car_2",
        "allowSelfLink": true
      }
    ]
  }
}
